{
  "SITREP Data": [
    {
      "Date": 44413,
      "Status": "Complete",
      "Mission #": "20251116_01",
      "Base MSN #": "20251116_VB",
      "Aircraft #": 200079,
      "Scheduled Launch": 44413.47222222222,
      "Launch Time ": 0.4722222222222222,
      "Recovery Time": 0.5027777777777778,
      "Hours": 0.73,
      "Tach Time": 1.1,
      "Hover Time": 0.1,
      "Manual Control": "No",
      "Payload 1": "Dummy",
      "Payload 2": "Comms Relay-123",
      "Weather": "Weather - Clear",
      "Winds": "070/11",
      "OAT": 33,
      "Risk Level": "Low",
      "Fuel In (Actual)": 16,
      "Fuel Out  (Actual)": 12.6,
      "TOIs": 0
    },
    {
      "Date": 44414,
      "Status": "Complete",
      "Aircraft #": 200080,
      "Scheduled Launch": 0.3402777777777778,
      "Launch Time ": 0.3402777777777778,
      "Recovery Time": 0.3958333333333333,
      "Hours": 1.33,
      "Tach Time": 1.4,
      "Hover Time": 0.1,
      "Manual Control": "No",
      "Payload 1": "Dummy",
      "Payload 2": "Comms Relay-123",
      "Weather": "Weather - Clear",
      "Winds": "058/17",
      "OAT": 26,
      "Risk Level": "Low",
      "Fuel In (Actual)": 16,
      "Fuel Out  (Actual)": 11.2
    },
    {
      "Date": 44414,
      "Status": "Complete",
      "Aircraft #": 200079,
      "Scheduled Launch": 0.5208333333333334,
      "Launch Time ": 0.5208333333333334,
      "Recovery Time": 0.625,
      "Hours": 2.5,
      "Tach Time": 3,
      "Hover Time": 0.1,
      "Manual Control": "No",
      "Payload 1": "Other",
      "Payload 2": "Comms Relay-123",
      "Weather": "Weather - Clear",
      "Winds": "258/8",
      "OAT": 26.6,
      "Risk Level": "Low",
      "Fuel In (Actual)": 20,
      "Fuel Out  (Actual)": 9
    },
    {
      "Date": 44453,
      "Status": "Complete",
      "Aircraft #": 200085,
      "Scheduled Launch": 0.6229166666666667,
      "Launch Time ": 0.6229166666666667,
      "Recovery Time": 0.7819444444444444,
      "Hours": 3.82,
      "Tach Time": 4.1,
      "Hover Time": 0.1,
      "Manual Control": "No",
      "Payload 1": "EO950",
      "Payload 2": "Comms Relay-123",
      "Weather": "Weather - Clear",
      "Winds": "305@22kts",
      "OAT": 32,
      "Risk Level": "Low",
      "Fuel In (Actual)": 27,
      "Fuel Out  (Actual)": 14,
      "Fuel Burn": 3.4031413612565444,
      "Notes": "unscheduled flight"
    },
    {
      "Date": 44454,
      "Status": "Complete",
      "Aircraft #": 200085,
      "Scheduled Launch": 0.5,
      "Launch Time ": 0.5173611111111112,
      "Recovery Time": 0.8048611111111111,
      "Hours": 6.9,
      "Tach Time": 7.1,
      "Hover Time": 0.1,
      "Manual Control": "No",
      "Payload 1": "EO950",
      "Payload 2": "Comms Relay-123",
      "REASON for Cancel, Abort or Delay": "Delay - Ship - Other",
      "Weather": "Weather - Clear",
      "Winds": "272@22kts",
      "OAT": 32,
      "Risk Level": "Low",
      "Fuel In (Actual)": 31,
      "Fuel Out  (Actual)": 4.5,
      "Fuel Burn": 3.8405797101449273
    },
    {
      "Date": 44460,
      "Status": "CNX",
      "Aircraft #": 200080,
      "Scheduled Launch": 0,
      "Hours": 0,
      "REASON for Cancel, Abort or Delay": "Cancelled - Weather - Rain",
      "Weather": "Weather - Rain",
      "Winds": "330@14kts",
      "OAT": 26,
      "Risk Level": "Low",
      "Fuel In (Actual)": 33,
      "Fuel Out  (Actual)": 33
    },
    {
      "Date": 44461,
      "Status": "CNX",
      "Aircraft #": 200080,
      "Scheduled Launch": 0.8333333333333334,
      "Hours": 0,
      "REASON for Cancel, Abort or Delay": "Cancelled - Weather - Low Ceiling",
      "Weather": "Weather - Low Ceiling",
      "Winds": "330@18kts",
      "OAT": 28,
      "Risk Level": "Low",
      "Fuel In (Actual)": 31,
      "Fuel Out  (Actual)": 31
    },
    {
      "Date": 44462,
      "Status": "CNX",
      "Aircraft #": 200080,
      "Scheduled Launch": 0,
      "Hours": 0,
      "REASON for Cancel, Abort or Delay": "Cancelled - Weather - Low Ceiling",
      "Weather": "Weather - Low Ceiling",
      "Fuel In (Actual)": 34,
      "Fuel Out  (Actual)": 34
    },
    {
      "Date": 44463,
      "Status": "Delay",
      "Aircraft #": 200080,
      "Scheduled Launch": 0,
      "Hours": 0,
      "REASON for Cancel, Abort or Delay": "Delay - Back Up AV Used",
      "Fuel In (Actual)": 32,
      "Fuel Out  (Actual)": 32,
      "Notes": "Launch cancelled launch button/launcher issues"
    },
    {
      "Date": 44463,
      "Status": "Delay",
      "Aircraft #": 200079,
      "Launch Time ": 0.3263888888888889,
      "Recovery Time": 0.5951388888888889,
      "Hours": 6.45,
      "Tach Time": 6.8,
      "Hover Time": 0.1,
      "Manual Control": "No",
      "Payload 1": "EO950",
      "Payload 2": "Comms Relay-123",
      "REASON for Cancel, Abort or Delay": "Delay - Ground Equipment",
      "Weather": "Weather - Low Ceiling",
      "Winds": "030@10kts",
      "OAT": 30,
      "Risk Level": "Low",
      "Fuel In (Actual)": 32,
      "Fuel Out  (Actual)": 7.8,
      "Fuel Burn": 3.751937984496124,
      "Notes": "Unscheduled flight after night cancelled"
    },
    {
      "Date": 44464,
      "Status": "Complete",
      "Aircraft #": 200080,
      "Launch Time ": 0.7965277777777777,
      "Recovery Time": 0.9868055555555556,
      "Hours": 4.57,
      "Tach Time": 4.8,
      "Hover Time": 0.1,
      "Manual Control": "No",
      "Payload 1": "EO960",
      "Payload 2": "Comms Relay-123",
      "Weather": "Weather - Rain - Light",
      "Winds": "335@10kts",
      "OAT": 28,
      "Risk Level": "Low",
      "Fuel In (Actual)": 32,
      "Fuel Out  (Actual)": 15.6,
      "Fuel Burn": 3.5886214442013125,
      "Notes": "unscheduled flight"
    },
    {
      "Date": 44465,
      "Status": "Delay",
      "Aircraft #": 200080,
      "Scheduled Launch": 0.7916666666666666,
      "Launch Time ": 0.8125,
      "Recovery Time": 0.9819444444444444,
      "Hours": 4.07,
      "Tach Time": 4.2,
      "Hover Time": 0.1,
      "Manual Control": "No",
      "Payload 1": "EO960",
      "Payload 2": "Comms Relay-123",
      "REASON for Cancel, Abort or Delay": "Delay - Weather - Rain",
      "Weather": "Weather - Rain - Light",
      "Winds": "322@12",
      "OAT": 30,
      "Risk Level": "Low",
      "Fuel In (Actual)": 24,
      "Fuel Out  (Actual)": 11.2,
      "Fuel Burn": 3.1449631449631448,
      "Notes": "Delayed due to rain ship sped away from shower launched soon after"
    },
    {
      "Date": 44467,
      "Status": "Delay",
      "Aircraft #": 200080,
      "Scheduled Launch": 0.16666666666666666,
      "Launch Time ": 0.19236111111111112,
      "Recovery Time": 0.49583333333333335,
      "Hours": 7.28,
      "Tach Time": 7.5,
      "Hover Time": 0.1,
      "Manual Control": "No",
      "Payload 1": "EO960",
      "Payload 2": "Comms Relay-123",
      "REASON for Cancel, Abort or Delay": "Delay - Ground Equipment",
      "Weather": "Weather - Rain - Light",
      "Winds": "145@11",
      "OAT": 28,
      "Risk Level": "Low",
      "Fuel In (Actual)": 35,
      "Fuel Out  (Actual)": 8.8,
      "Fuel Burn": 3.5989010989010985,
      "Notes": "Delayed to to launch pad not connecting/switch pad out and launched"
    },
    {
      "Date": 44468,
      "Status": "Delay",
      "Aircraft #": 200080,
      "Scheduled Launch": 0.4166666666666667,
      "Launch Time ": 0.4409722222222222,
      "Recovery Time": 0.6479166666666667,
      "Hours": 4.97,
      "Tach Time": 5.2,
      "Hover Time": 0.1,
      "Manual Control": "No",
      "Payload 1": "EO960",
      "Payload 2": "Comms Relay-123",
      "REASON for Cancel, Abort or Delay": "Delay - Weather - Rain - Heavy",
      "Weather": "Weather - Rain - Light",
      "Winds": "340@12",
      "OAT": 29,
      "Risk Level": "Low",
      "Fuel In (Actual)": 22,
      "Fuel Out  (Actual)": 5,
      "Fuel Burn": 3.420523138832998,
      "Notes": "Delayed due to heavy rain as soon as passed launched aircraft"
    },
    {
      "Date": 44468,
      "Status": "Complete",
      "Aircraft #": 200079,
      "Launch Time ": 0.6090277777777777,
      "Recovery Time": 0.7708333333333334,
      "Hours": 3.88,
      "Tach Time": 4.1,
      "Hover Time": 0.1,
      "Manual Control": "No",
      "Payload 1": "EO950",
      "Payload 2": "Comms Relay-123",
      "Weather": "Weather - Clear",
      "Winds": "320@6",
      "OAT": 23.9,
      "Risk Level": "Low",
      "Fuel In (Actual)": 22,
      "Fuel Out  (Actual)": 7.6,
      "Fuel Burn": 3.711340206185567,
      "Notes": "relief on station aircraft. "
    },
    {
      "Date": 44470,
      "Status": "Delay",
      "Aircraft #": 200080,
      "Scheduled Launch": 0.5416666666666666,
      "Launch Time ": 0.5625,
      "Recovery Time": 0.8888888888888888,
      "Hours": 7.83,
      "Tach Time": 8,
      "Hover Time": 0.1,
      "Manual Control": "No",
      "Payload 1": "EO960",
      "Payload 2": "Comms Relay-123",
      "REASON for Cancel, Abort or Delay": "Delay - Weather - Winds - Gusting",
      "Weather": "Weather - Wind",
      "Winds": "287@13",
      "OAT": 28.5,
      "Risk Level": "Low",
      "Fuel In (Actual)": 32,
      "Fuel Out  (Actual)": 7.5,
      "Fuel Burn": 3.128991060025543,
      "Notes": "Delayed due to winds exceeding 25kts and gust up to 30kts"
    },
    {
      "Date": 44472,
      "Status": "CNX",
      "Aircraft #": 200080,
      "Scheduled Launch": 0.7083333333333334,
      "Launch Time ": 0.7118055555555556,
      "Recovery Time": 0.7125,
      "Hours": 0.02,
      "Tach Time": 0.2,
      "Hover Time": 0.1,
      "Manual Control": "No",
      "Payload 1": "EO960",
      "Payload 2": "Comms Relay-123",
      "REASON for Cancel, Abort or Delay": "Cancelled - Equipment Failure",
      "Winds": "198@17",
      "OAT": 28.2,
      "Risk Level": "Low",
      "Fuel In (Actual)": 26,
      "Fuel Burn": "",
      "Notes": "Aircraft mishap in flight. Lost at sea. "
    },
    {
      "Date": 44473,
      "Status": "Delay",
      "Aircraft #": 200079,
      "Scheduled Launch": 0.5416666666666666,
      "Launch Time ": 0.5763888888888888,
      "Recovery Time": 0.7986111111111112,
      "Hours": 5.33,
      "Tach Time": 5.5,
      "Hover Time": 0.1,
      "Manual Control": "No",
      "Payload 1": "EO950",
      "Payload 2": "Comms Relay-123",
      "REASON for Cancel, Abort or Delay": "Delay - Engine",
      "Weather": "Weather - Wind",
      "Winds": "225@18",
      "OAT": 29,
      "Risk Level": "Low",
      "Fuel In (Actual)": 33,
      "Fuel Out  (Actual)": 14.5,
      "Fuel Burn": "",
      "Notes": "Delayed becouse of above aircrat."
    },
    {
      "Date": 44474,
      "Status": "CNX",
      "Aircraft #": 200085,
      "Scheduled Launch": 0.2916666666666667,
      "Hours": 0,
      "REASON for Cancel, Abort or Delay": "Cancelled - Equipment Failure",
      "Fuel Burn": "",
      "Notes": "Midwing red on enunciation panel during engine run"
    },
    {
      "Date": 44475,
      "Status": "Complete",
      "Aircraft #": 200079,
      "Launch Time ": 0.3229166666666667,
      "Recovery Time": 0.6465277777777778,
      "Hours": 7.77,
      "Tach Time": 8,
      "Hover Time": 0.1,
      "Manual Control": "No",
      "Payload 1": "EO950",
      "Payload 2": "Comms Relay-123",
      "Weather": "Weather - Clear",
      "Winds": "066@10",
      "OAT": 28.3,
      "Risk Level": "Low",
      "Fuel In (Actual)": 34,
      "Fuel Out  (Actual)": 7.5,
      "Fuel Burn": 3.4105534105534105,
      "Notes": "After repairs was verified launched to support TOI mission. V-BAT200079 launched for a successful mission event (7.8 hrs). Experienced severe comms degradation at 20-23nm from ship. Multiple loss comms routes were executed until ship was in the <25nm range. Working through the issues in flight, TOI was still located and tracked via V-BAT200079. 1 TOI, 3 people, 2338KG seized. Currently troubleshooting comms issues.  Starlink troubleshooting was successful, and V-BAT200079 files have been sent back for analysis. "
    },
    {
      "Date": 44476,
      "Status": "Complete",
      "Aircraft #": 200079,
      "Launch Time ": 0.7465277777777778,
      "Recovery Time": 0.9479166666666666,
      "Hours": 4.83,
      "Tach Time": 5.3,
      "Hover Time": 0.1,
      "Manual Control": "No",
      "Payload 1": "EO950",
      "Payload 2": "Comms Relay-123",
      "Weather": "Weather - Clear",
      "Winds": "265@8",
      "OAT": 28,
      "Risk Level": "Low",
      "Fuel In (Actual)": 30,
      "Fuel Out  (Actual)": 11.2,
      "Fuel Burn": 3.8923395445134576,
      "Notes": "unscheduled mission to support TOI"
    },
    {
      "Date": 44477,
      "Status": "Complete",
      "Aircraft #": 200079,
      "Launch Time ": 0.21388888888888888,
      "Recovery Time": 0.43333333333333335,
      "Hours": 5.27,
      "Tach Time": 5.5,
      "Hover Time": 0.1,
      "Manual Control": "No",
      "Payload 1": "EO950",
      "Payload 2": "Comms Relay-123",
      "Weather": "Weather - Clear",
      "Winds": "300@13",
      "OAT": 29,
      "Risk Level": "Low",
      "Fuel In (Actual)": 30,
      "Fuel Out  (Actual)": 12.5,
      "Fuel Burn": 3.3206831119544593,
      "Notes": "unscheduled mission to support TOI"
    },
    {
      "Date": 44479,
      "Status": "Complete",
      "Aircraft #": 200079,
      "Launch Time ": 0.5465277777777777,
      "Recovery Time": 0.7777777777777778,
      "Hours": 5.55,
      "Tach Time": 5.7,
      "Hover Time": 0.1,
      "Manual Control": "No",
      "Payload 1": "EO950",
      "Payload 2": "Comms Relay-123",
      "Weather": "Weather - Clear",
      "Winds": "252@12",
      "OAT": 29.2,
      "Risk Level": "Low",
      "Fuel In (Actual)": 30,
      "Fuel Out  (Actual)": 13.2,
      "Fuel Burn": 3.027027027027027,
      "Notes": "unscheduled mission to support TOI"
    },
    {
      "Date": 44483,
      "Status": "CNX",
      "Aircraft #": 200079,
      "Hours": 0,
      "REASON for Cancel, Abort or Delay": "Cancelled - Weather - Lightning",
      "Weather": "Weather - Lightning",
      "Fuel Burn": "",
      "Notes": "delayed for rain/low ceilings and finally cancelled due to lightning/thunderstorms on station"
    },
    {
      "Date": 44484,
      "Status": "CNX",
      "Aircraft #": 200079,
      "Scheduled Launch": 0.75,
      "Hours": 0,
      "REASON for Cancel, Abort or Delay": "Cancelled - Weather - Rain - Heavy",
      "Weather": "Weather - Rain - Heavy",
      "Fuel Burn": "",
      "Notes": "Cancelled due to heavy rain and low ceilings"
    },
    {
      "Date": 44490,
      "Status": "Complete",
      "Aircraft #": 200079,
      "Scheduled Launch": 0.875,
      "Launch Time ": 0.7986111111111112,
      "Recovery Time": 0.06527777777777778,
      "Hours": 6.4,
      "Tach Time": 6.7,
      "Hover Time": 0.1,
      "Manual Control": "No",
      "Payload 1": "EO960",
      "Payload 2": "Comms Relay-123",
      "Weather": "Weather - Winds - Gusting",
      "Winds": "330@22",
      "OAT": 30,
      "Risk Level": "Low",
      "Fuel In (Actual)": 28,
      "Fuel Out  (Actual)": 6.5,
      "Fuel Burn": 3.359375,
      "Notes": "Launched early for mission support"
    },
    {
      "Date": 44492,
      "Status": "Delay",
      "Aircraft #": 200079,
      "Scheduled Launch": 0.16666666666666666,
      "Launch Time ": 0.2152777777777778,
      "Recovery Time": 0.4875,
      "Hours": 6.53,
      "Tach Time": 6.7,
      "Hover Time": 0.1,
      "Manual Control": "No",
      "Payload 1": "EO960",
      "Payload 2": "Comms Relay-123",
      "REASON for Cancel, Abort or Delay": "Delay - Camera Replaced",
      "Weather": "Weather - Low Ceiling",
      "Winds": "344@19",
      "OAT": 21,
      "Risk Level": "Low",
      "Fuel In (Actual)": 34.2,
      "Fuel Out  (Actual)": 13,
      "Fuel Burn": 3.2465543644716695,
      "Notes": "delayed launch for camera issues poor weather conditions had to land early"
    },
    {
      "Date": 44492,
      "Status": "CNX",
      "Aircraft #": 200085,
      "Launch Time ": 0.66875,
      "Recovery Time": 0.66875,
      "Hours": 0,
      "Tach Time": 0.1,
      "REASON for Cancel, Abort or Delay": "Cancelled - Equipment Failure",
      "Fuel Burn": "",
      "Notes": "Aircraft came off launcher during engine run tipping over. Loss of aircraft"
    },
    {
      "Date": 44494,
      "Status": "CNX",
      "Aircraft #": 200079,
      "Scheduled Launch": 0.8333333333333334,
      "Hours": 0,
      "REASON for Cancel, Abort or Delay": "Cancelled - Engine",
      "Fuel Burn": "",
      "Notes": "Flight with V-BAT200079 was scheduled for 2000L. After engine runs and high power, pitch and roll of the ship visually looked more drastic than what crew was used to. V-BAT200079 had significant movement inside the launcher and looked very unstable as called out by the AO/AV during engine runs. Multiple checks with the ship confirmed our max limits for both pitch and roll. The entire evolution was halted and a discussion amongst the crew utilizing ORM and sound judgement was conducted. Engine was shut down as ship adjusted course for safety. After a second preflight, V-BAT200079 would not achieve the minimum 6850 RPM during max power checks. Three separate high-power runs were performed on the flight deck with each one failing RPM checks by a significant amount. Engine was shut down and moved in hangar for troubleshooting. Both Injectors, and new vaporizer have been installed. "
    },
    {
      "Date": 44496,
      "Status": "Delay",
      "Aircraft #": 200079,
      "Scheduled Launch": 0.6666666666666666,
      "Launch Time ": 0.7055555555555556,
      "Recovery Time": 0.9326388888888889,
      "Hours": 5.45,
      "Tach Time": 5.8,
      "Hover Time": 0.1,
      "Manual Control": "No",
      "Payload 1": "EO960",
      "Payload 2": "Comms Relay-123",
      "REASON for Cancel, Abort or Delay": "Delay - Ship - Other",
      "Weather": "Weather - Low Ceiling",
      "Winds": "040@16",
      "OAT": 23.6,
      "Risk Level": "Low",
      "Fuel In (Actual)": 27,
      "Fuel Out  (Actual)": 11,
      "Fuel Burn": 2.935779816513761,
      "Notes": "Delayed due to ship speed/manuever around another vessel before restarting preflight for tracking ins. Flight with V-BAT200079 at 1600L (5.5hrs). Investigated ships radar contacts with no suspicious or unusual activity found. Upon landing in 9kt winds, V-BAT200079 overshot the landing pad by approximately 15 feet. V-BAT200079 then stabilized and overflew the pad in the opposite direction and landed 6 feet away from the pad. Reaching out to fleet support for guidance on this issue."
    },
    {
      "Date": 44499,
      "Status": "Complete",
      "Aircraft #": 200079,
      "Scheduled Launch": 0.875,
      "Launch Time ": 0.7951388888888888,
      "Recovery Time": 0.9270833333333334,
      "Hours": 3.17,
      "Tach Time": 3.5,
      "Hover Time": 0.1,
      "Manual Control": "No",
      "Payload 1": "EO960",
      "Payload 2": "Comms Relay-123",
      "Weather": "Weather - Low Ceiling",
      "Winds": "345@17",
      "OAT": 23,
      "Risk Level": "Low",
      "Fuel In (Actual)": 21,
      "Fuel Out  (Actual)": 10,
      "Fuel Burn": 3.470031545741325,
      "Notes": "Launched early for mission support"
    },
    {
      "Date": 44500,
      "Status": "Complete",
      "Aircraft #": 200079,
      "Launch Time ": 0.4236111111111111,
      "Recovery Time": 0.5847222222222223,
      "Hours": 3.87,
      "Tach Time": 3.9,
      "Hover Time": 0.1,
      "Manual Control": "No",
      "Payload 1": "EO960",
      "Payload 2": "Comms Relay-123",
      "Weather": "Weather - Low Ceiling",
      "Winds": "290@16",
      "OAT": 22,
      "Risk Level": "Low",
      "Fuel In (Actual)": 22,
      "Fuel Out  (Actual)": 10.5,
      "Fuel Burn": 2.9715762273901807,
      "Notes": "unscheduled flight to support mission"
    },
    {
      "Date": 44503,
      "Status": "Complete",
      "Aircraft #": 200079,
      "Launch Time ": 0.6625,
      "Recovery Time": 0.9298611111111111,
      "Hours": 6.42,
      "Tach Time": 6.5,
      "Hover Time": 0.1,
      "Manual Control": "No",
      "Payload 1": "EO960",
      "Payload 2": "Comms Relay-123",
      "Weather": "Weather - Clear",
      "Winds": "310@12",
      "OAT": 24,
      "Risk Level": "Low",
      "Fuel In (Actual)": 28,
      "Fuel Out  (Actual)": 10.5,
      "Fuel Burn": 2.7258566978193146,
      "Notes": "unscheduled mission to support TOI"
    },
    {
      "Date": 44504,
      "Status": "Delay",
      "Aircraft #": 200079,
      "Scheduled Launch": 0.6666666666666666,
      "Launch Time ": 0.6840277777777778,
      "Recovery Time": 0.8590277777777777,
      "Hours": 4.2,
      "Tach Time": 4.3,
      "Hover Time": 0.1,
      "Manual Control": "No",
      "Payload 1": "EO960",
      "Payload 2": "Comms Relay-123",
      "REASON for Cancel, Abort or Delay": "Delay - Ship - Other",
      "Weather": "Weather - Low Ceiling",
      "Winds": "160@15",
      "OAT": 25,
      "Risk Level": "Low",
      "Fuel In (Actual)": 28,
      "Fuel Out  (Actual)": 13.5,
      "Fuel Burn": 3.452380952380952,
      "Notes": "unscheduled mission to support TOI"
    }
  ],
  "Equipment Data": [
    {
      "Data": "Date",
      "__EMPTY": "Category",
      "__EMPTY_1": "Equipment",
      "__EMPTY_2": "Serial Number",
      "__EMPTY_3": "Status",
      "__EMPTY_4": "Location",
      "__EMPTY_5": "Software",
      "__EMPTY_6": "Comments"
    },
    {
      "Data": 44469,
      "__EMPTY": "Aircraft",
      "__EMPTY_1": "V-BAT",
      "__EMPTY_2": "200079",
      "__EMPTY_3": "FMC",
      "__EMPTY_4": "",
      "__EMPTY_5": "1.3.7",
      "__EMPTY_6": ""
    },
    {
      "Data": 44469,
      "__EMPTY": "Aircraft",
      "__EMPTY_1": "V-BAT",
      "__EMPTY_2": "200080",
      "__EMPTY_3": "NMC",
      "__EMPTY_4": "",
      "__EMPTY_5": "1.2.1",
      "__EMPTY_6": "Lost at sea"
    },
    {
      "Data": 44469,
      "__EMPTY": "Aircraft",
      "__EMPTY_1": "V-BAT",
      "__EMPTY_2": "200085",
      "__EMPTY_3": "NMC",
      "__EMPTY_4": "",
      "__EMPTY_5": "1.3.7",
      "__EMPTY_6": ""
    },
    {
      "Data": 44469,
      "__EMPTY": "Payloads",
      "__EMPTY_1": "EO950",
      "__EMPTY_2": "950202",
      "__EMPTY_3": "FMC",
      "__EMPTY_4": "Aircraft 079",
      "__EMPTY_5": "1.3.7",
      "__EMPTY_6": ""
    },
    {
      "Data": 44469,
      "__EMPTY": "Payloads",
      "__EMPTY_1": "EO950",
      "__EMPTY_2": "950286",
      "__EMPTY_3": "NMC",
      "__EMPTY_4": "Aircraft 085",
      "__EMPTY_5": "1.2.1",
      "__EMPTY_6": "Lost at sea"
    },
    {
      "Data": 44469,
      "__EMPTY": "Payloads",
      "__EMPTY_1": "MWIR 3.6",
      "__EMPTY_2": "960202",
      "__EMPTY_3": "FMC",
      "__EMPTY_4": "Hangar",
      "__EMPTY_5": "1.3.7",
      "__EMPTY_6": ""
    },
    {
      "Data": 44469,
      "__EMPTY": "Payloads",
      "__EMPTY_1": "MWIR 3.6",
      "__EMPTY_2": "960198",
      "__EMPTY_3": "NMC",
      "__EMPTY_4": "Aircraft 080",
      "__EMPTY_5": "",
      "__EMPTY_6": ""
    },
    {
      "Data": 44469,
      "__EMPTY": "Payloads",
      "__EMPTY_1": "Comms Relay",
      "__EMPTY_2": "123",
      "__EMPTY_3": "FMC",
      "__EMPTY_4": "",
      "__EMPTY_5": "",
      "__EMPTY_6": ""
    },
    {
      "Data": 44469,
      "__EMPTY": "Payloads",
      "__EMPTY_1": "Comms Relay",
      "__EMPTY_2": "456",
      "__EMPTY_3": "FMC",
      "__EMPTY_4": "",
      "__EMPTY_5": "",
      "__EMPTY_6": ""
    },
    {
      "Data": 44469,
      "__EMPTY": "Launchers",
      "__EMPTY_1": "Launcher",
      "__EMPTY_2": "200-K0105-02C - 1",
      "__EMPTY_3": "FMC",
      "__EMPTY_4": "",
      "__EMPTY_5": "",
      "__EMPTY_6": ""
    },
    {
      "Data": 44469,
      "__EMPTY": "Launchers",
      "__EMPTY_1": "Launcher",
      "__EMPTY_2": "200-K0105-02C - 2",
      "__EMPTY_3": "FMC",
      "__EMPTY_4": "",
      "__EMPTY_5": "",
      "__EMPTY_6": ""
    },
    {
      "Data": 44469,
      "__EMPTY": "Launchers",
      "__EMPTY_1": "Launcher",
      "__EMPTY_2": "200-K0105-02C - 3",
      "__EMPTY_3": "FMC",
      "__EMPTY_4": "",
      "__EMPTY_5": "",
      "__EMPTY_6": ""
    },
    {
      "Data": 44469,
      "__EMPTY": "Launchers",
      "__EMPTY_1": "Launcher",
      "__EMPTY_2": "200-K0105-02C - 4",
      "__EMPTY_3": "FMC",
      "__EMPTY_4": "",
      "__EMPTY_5": "",
      "__EMPTY_6": ""
    },
    {
      "Data": 44469,
      "__EMPTY": "GCS",
      "__EMPTY_1": "MaxVision",
      "__EMPTY_2": "MO-72199",
      "__EMPTY_3": "FMC",
      "__EMPTY_4": "",
      "__EMPTY_5": "1.3.6",
      "__EMPTY_6": ""
    },
    {
      "Data": 44469,
      "__EMPTY": "GCS",
      "__EMPTY_1": "MaxVision",
      "__EMPTY_2": "MO-71118",
      "__EMPTY_3": "FMC",
      "__EMPTY_4": "",
      "__EMPTY_5": "1.3.6",
      "__EMPTY_6": ""
    },
    {
      "Data": 44469,
      "__EMPTY": "Tablets",
      "__EMPTY_1": "GCS Tablet",
      "__EMPTY_2": "MO-70993",
      "__EMPTY_3": "FMC",
      "__EMPTY_4": "",
      "__EMPTY_5": "",
      "__EMPTY_6": "VBC"
    },
    {
      "Data": 44469,
      "__EMPTY": "Tablets",
      "__EMPTY_1": "GCS Tablet",
      "__EMPTY_2": "MO-71096",
      "__EMPTY_3": "NMC",
      "__EMPTY_4": "",
      "__EMPTY_5": "",
      "__EMPTY_6": "VBC"
    },
    {
      "Data": 44469,
      "__EMPTY": "Tablets",
      "__EMPTY_1": "GCS Tablet",
      "__EMPTY_2": "MO-31541",
      "__EMPTY_3": "FMC",
      "__EMPTY_4": "",
      "__EMPTY_5": "",
      "__EMPTY_6": "Kutta"
    },
    {
      "Data": 44469,
      "__EMPTY": "MPU5",
      "__EMPTY_1": "MPU5",
      "__EMPTY_2": "100576",
      "__EMPTY_3": "FMC",
      "__EMPTY_4": "",
      "__EMPTY_5": "",
      "__EMPTY_6": "Omni 447 (GCS Accessory Kit MO-70193 Named radio GCS Hangar)"
    },
    {
      "Data": 44469,
      "__EMPTY": "MPU5",
      "__EMPTY_1": "MPU6",
      "__EMPTY_2": "66488",
      "__EMPTY_3": "FMC",
      "__EMPTY_4": "",
      "__EMPTY_5": "",
      "__EMPTY_6": "Omni 247 KIT"
    },
    {
      "Data": 44469,
      "__EMPTY": "MPU5",
      "__EMPTY_1": "MPU7",
      "__EMPTY_2": "67859",
      "__EMPTY_3": "FMC",
      "__EMPTY_4": "",
      "__EMPTY_5": "",
      "__EMPTY_6": "Omni 433 KIT"
    },
    {
      "Data": 44469,
      "__EMPTY": "MPU5",
      "__EMPTY_1": "MPU8",
      "__EMPTY_2": "54056",
      "__EMPTY_3": "FMC",
      "__EMPTY_4": "",
      "__EMPTY_5": "",
      "__EMPTY_6": "Omni 082 KIT"
    },
    {
      "Data": 44469,
      "__EMPTY": "MPU5",
      "__EMPTY_1": "MPU9",
      "__EMPTY_2": "82140",
      "__EMPTY_3": "FMC",
      "__EMPTY_4": "",
      "__EMPTY_5": "",
      "__EMPTY_6": "Omni 462-KIT also marked as MO-01408"
    },
    {
      "Data": 44469,
      "__EMPTY": "MPU5",
      "__EMPTY_1": "Mast Antenna",
      "__EMPTY_2": "85758",
      "__EMPTY_3": "FMC",
      "__EMPTY_4": "",
      "__EMPTY_5": "",
      "__EMPTY_6": "Omni 409 (installed omni on mast)"
    },
    {
      "Data": 44469,
      "__EMPTY": "MPU5",
      "__EMPTY_1": "FWD GDT",
      "__EMPTY_2": "50233",
      "__EMPTY_3": "FMC",
      "__EMPTY_4": "",
      "__EMPTY_5": "",
      "__EMPTY_6": "Tracker 7 (FWD GDT installed internal componets have been switched) 4007 MTS"
    },
    {
      "Data": 44469,
      "__EMPTY": "MPU5",
      "__EMPTY_1": "AFT GDT",
      "__EMPTY_2": "50095",
      "__EMPTY_3": "FMC",
      "__EMPTY_4": "",
      "__EMPTY_5": "",
      "__EMPTY_6": "Tracker 160 (AFT GDT installed) 4005 MTS"
    },
    {
      "Data": 44515,
      "__EMPTY": "Aircraft",
      "__EMPTY_1": "V-BAT",
      "__EMPTY_2": "200079",
      "__EMPTY_3": "FMC",
      "__EMPTY_4": "",
      "__EMPTY_5": "1.3.7",
      "__EMPTY_6": ""
    },
    {
      "Data": 44515,
      "__EMPTY": "Aircraft",
      "__EMPTY_1": "V-BAT",
      "__EMPTY_2": "200080",
      "__EMPTY_3": "NMC",
      "__EMPTY_4": "",
      "__EMPTY_5": "1.2.1",
      "__EMPTY_6": "Lost at sea"
    },
    {
      "Data": 44515,
      "__EMPTY": "Aircraft",
      "__EMPTY_1": "V-BAT",
      "__EMPTY_2": "200085",
      "__EMPTY_3": "NMC",
      "__EMPTY_4": "",
      "__EMPTY_5": "1.3.7",
      "__EMPTY_6": ""
    },
    {
      "Data": 44515,
      "__EMPTY": "Payloads",
      "__EMPTY_1": "EO950",
      "__EMPTY_2": "950202",
      "__EMPTY_3": "FMC",
      "__EMPTY_4": "Aircraft 079",
      "__EMPTY_5": "1.3.7",
      "__EMPTY_6": ""
    },
    {
      "Data": 44515,
      "__EMPTY": "Payloads",
      "__EMPTY_1": "EO950",
      "__EMPTY_2": "950286",
      "__EMPTY_3": "NMC",
      "__EMPTY_4": "Aircraft 085",
      "__EMPTY_5": "1.2.1",
      "__EMPTY_6": "Lost at sea"
    },
    {
      "Data": 44515,
      "__EMPTY": "Payloads",
      "__EMPTY_1": "MWIR 3.6",
      "__EMPTY_2": "960202",
      "__EMPTY_3": "FMC",
      "__EMPTY_4": "Hangar",
      "__EMPTY_5": "1.3.7",
      "__EMPTY_6": ""
    },
    {
      "Data": 44515,
      "__EMPTY": "Payloads",
      "__EMPTY_1": "MWIR 3.6",
      "__EMPTY_2": "960198",
      "__EMPTY_3": "NMC",
      "__EMPTY_4": "Aircraft 080",
      "__EMPTY_5": "",
      "__EMPTY_6": ""
    },
    {
      "Data": 44515,
      "__EMPTY": "Payloads",
      "__EMPTY_1": "Comms Relay",
      "__EMPTY_2": "123",
      "__EMPTY_3": "FMC",
      "__EMPTY_4": "",
      "__EMPTY_5": "",
      "__EMPTY_6": ""
    },
    {
      "Data": 44515,
      "__EMPTY": "Payloads",
      "__EMPTY_1": "Comms Relay",
      "__EMPTY_2": "456",
      "__EMPTY_3": "FMC",
      "__EMPTY_4": "",
      "__EMPTY_5": "",
      "__EMPTY_6": ""
    },
    {
      "Data": 44515,
      "__EMPTY": "Launchers",
      "__EMPTY_1": "Launcher",
      "__EMPTY_2": "200-K0105-02C - 1",
      "__EMPTY_3": "FMC",
      "__EMPTY_4": "",
      "__EMPTY_5": "",
      "__EMPTY_6": ""
    },
    {
      "Data": 44515,
      "__EMPTY": "Launchers",
      "__EMPTY_1": "Launcher",
      "__EMPTY_2": "200-K0105-02C - 2",
      "__EMPTY_3": "FMC",
      "__EMPTY_4": "",
      "__EMPTY_5": "",
      "__EMPTY_6": ""
    },
    {
      "Data": 44515,
      "__EMPTY": "Launchers",
      "__EMPTY_1": "Launcher",
      "__EMPTY_2": "200-K0105-02C - 3",
      "__EMPTY_3": "FMC",
      "__EMPTY_4": "",
      "__EMPTY_5": "",
      "__EMPTY_6": ""
    },
    {
      "Data": 44515,
      "__EMPTY": "Launchers",
      "__EMPTY_1": "Launcher",
      "__EMPTY_2": "200-K0105-02C - 4",
      "__EMPTY_3": "FMC",
      "__EMPTY_4": "",
      "__EMPTY_5": "",
      "__EMPTY_6": ""
    },
    {
      "Data": 44515,
      "__EMPTY": "GCS",
      "__EMPTY_1": "MaxVision",
      "__EMPTY_2": "MO-72199",
      "__EMPTY_3": "FMC",
      "__EMPTY_4": "",
      "__EMPTY_5": "1.3.6",
      "__EMPTY_6": ""
    },
    {
      "Data": 44515,
      "__EMPTY": "GCS",
      "__EMPTY_1": "MaxVision",
      "__EMPTY_2": "MO-71118",
      "__EMPTY_3": "FMC",
      "__EMPTY_4": "",
      "__EMPTY_5": "1.3.6",
      "__EMPTY_6": ""
    },
    {
      "Data": 44515,
      "__EMPTY": "Tablets",
      "__EMPTY_1": "GCS Tablet",
      "__EMPTY_2": "MO-70993",
      "__EMPTY_3": "FMC",
      "__EMPTY_4": "",
      "__EMPTY_5": "",
      "__EMPTY_6": "VBC"
    },
    {
      "Data": 44515,
      "__EMPTY": "Tablets",
      "__EMPTY_1": "GCS Tablet",
      "__EMPTY_2": "MO-71096",
      "__EMPTY_3": "NMC",
      "__EMPTY_4": "",
      "__EMPTY_5": "",
      "__EMPTY_6": "VBC"
    },
    {
      "Data": 44515,
      "__EMPTY": "Tablets",
      "__EMPTY_1": "GCS Tablet",
      "__EMPTY_2": "MO-31541",
      "__EMPTY_3": "FMC",
      "__EMPTY_4": "",
      "__EMPTY_5": "",
      "__EMPTY_6": "Kutta"
    },
    {
      "Data": 44515,
      "__EMPTY": "MPU5",
      "__EMPTY_1": "MPU5",
      "__EMPTY_2": "100576",
      "__EMPTY_3": "FMC",
      "__EMPTY_4": "",
      "__EMPTY_5": "",
      "__EMPTY_6": "Omni 447 (GCS Accessory Kit MO-70193 Named radio GCS Hangar)"
    },
    {
      "Data": 44515,
      "__EMPTY": "MPU5",
      "__EMPTY_1": "MPU6",
      "__EMPTY_2": "66488",
      "__EMPTY_3": "FMC",
      "__EMPTY_4": "",
      "__EMPTY_5": "",
      "__EMPTY_6": "Omni 247 KIT"
    },
    {
      "Data": 44515,
      "__EMPTY": "MPU5",
      "__EMPTY_1": "MPU7",
      "__EMPTY_2": "67859",
      "__EMPTY_3": "FMC",
      "__EMPTY_4": "",
      "__EMPTY_5": "",
      "__EMPTY_6": "Omni 433 KIT"
    },
    {
      "Data": 44515,
      "__EMPTY": "MPU5",
      "__EMPTY_1": "MPU8",
      "__EMPTY_2": "54056",
      "__EMPTY_3": "FMC",
      "__EMPTY_4": "",
      "__EMPTY_5": "",
      "__EMPTY_6": "Omni 082 KIT"
    },
    {
      "Data": 44515,
      "__EMPTY": "MPU5",
      "__EMPTY_1": "MPU9",
      "__EMPTY_2": "82140",
      "__EMPTY_3": "FMC",
      "__EMPTY_4": "",
      "__EMPTY_5": "",
      "__EMPTY_6": "Omni 462-KIT also marked as MO-01408"
    },
    {
      "Data": 44515,
      "__EMPTY": "MPU5",
      "__EMPTY_1": "Mast Antenna",
      "__EMPTY_2": "85758",
      "__EMPTY_3": "FMC",
      "__EMPTY_4": "",
      "__EMPTY_5": "",
      "__EMPTY_6": "Omni 409 (installed omni on mast)"
    },
    {
      "Data": 44515,
      "__EMPTY": "MPU5",
      "__EMPTY_1": "FWD GDT",
      "__EMPTY_2": "50233",
      "__EMPTY_3": "FMC",
      "__EMPTY_4": "",
      "__EMPTY_5": "",
      "__EMPTY_6": "Tracker 7 (FWD GDT installed internal componets have been switched) 4007 MTS"
    },
    {
      "Data": 44515,
      "__EMPTY": "MPU5",
      "__EMPTY_1": "AFT GDT",
      "__EMPTY_2": "50095",
      "__EMPTY_3": "FMC",
      "__EMPTY_4": "",
      "__EMPTY_5": "",
      "__EMPTY_6": "Tracker 160 (AFT GDT installed) 4005 MTS"
    },
    {
      "Data": 44511,
      "__EMPTY": "Aircraft",
      "__EMPTY_1": "V-BAT",
      "__EMPTY_2": "200079",
      "__EMPTY_3": "FMC",
      "__EMPTY_4": "",
      "__EMPTY_5": "1.3.7",
      "__EMPTY_6": ""
    },
    {
      "Data": 44511,
      "__EMPTY": "Aircraft",
      "__EMPTY_1": "V-BAT",
      "__EMPTY_2": "200080",
      "__EMPTY_3": "NMC",
      "__EMPTY_4": "",
      "__EMPTY_5": "1.2.1",
      "__EMPTY_6": "Lost at sea"
    },
    {
      "Data": 44511,
      "__EMPTY": "Aircraft",
      "__EMPTY_1": "V-BAT",
      "__EMPTY_2": "200085",
      "__EMPTY_3": "NMC",
      "__EMPTY_4": "",
      "__EMPTY_5": "1.3.7",
      "__EMPTY_6": ""
    },
    {
      "Data": 44511,
      "__EMPTY": "Payloads",
      "__EMPTY_1": "EO950",
      "__EMPTY_2": "950202",
      "__EMPTY_3": "FMC",
      "__EMPTY_4": "Aircraft 079",
      "__EMPTY_5": "1.3.7",
      "__EMPTY_6": ""
    },
    {
      "Data": 44511,
      "__EMPTY": "Payloads",
      "__EMPTY_1": "EO950",
      "__EMPTY_2": "950286",
      "__EMPTY_3": "NMC",
      "__EMPTY_4": "Aircraft 085",
      "__EMPTY_5": "1.2.1",
      "__EMPTY_6": "Lost at sea"
    },
    {
      "Data": 44511,
      "__EMPTY": "Payloads",
      "__EMPTY_1": "MWIR 3.6",
      "__EMPTY_2": "960202",
      "__EMPTY_3": "FMC",
      "__EMPTY_4": "Hangar",
      "__EMPTY_5": "1.3.7",
      "__EMPTY_6": ""
    },
    {
      "Data": 44511,
      "__EMPTY": "Payloads",
      "__EMPTY_1": "MWIR 3.6",
      "__EMPTY_2": "960198",
      "__EMPTY_3": "NMC",
      "__EMPTY_4": "Aircraft 080",
      "__EMPTY_5": "",
      "__EMPTY_6": ""
    },
    {
      "Data": 44510,
      "__EMPTY": "Aircraft",
      "__EMPTY_1": "V-BAT",
      "__EMPTY_2": "200079",
      "__EMPTY_3": "FMC",
      "__EMPTY_4": "",
      "__EMPTY_5": "1.3.7",
      "__EMPTY_6": ""
    },
    {
      "Data": 44510,
      "__EMPTY": "Aircraft",
      "__EMPTY_1": "V-BAT",
      "__EMPTY_2": "200080",
      "__EMPTY_3": "NMC",
      "__EMPTY_4": "",
      "__EMPTY_5": "1.2.1",
      "__EMPTY_6": "Lost at sea"
    },
    {
      "Data": 44510,
      "__EMPTY": "Aircraft",
      "__EMPTY_1": "V-BAT",
      "__EMPTY_2": "200085",
      "__EMPTY_3": "NMC",
      "__EMPTY_4": "",
      "__EMPTY_5": "1.3.7",
      "__EMPTY_6": ""
    },
    {
      "Data": 44510,
      "__EMPTY": "Payloads",
      "__EMPTY_1": "EO950",
      "__EMPTY_2": "950202",
      "__EMPTY_3": "FMC",
      "__EMPTY_4": "Aircraft 079",
      "__EMPTY_5": "1.3.7",
      "__EMPTY_6": ""
    },
    {
      "Data": 44510,
      "__EMPTY": "Payloads",
      "__EMPTY_1": "EO950",
      "__EMPTY_2": "950286",
      "__EMPTY_3": "NMC",
      "__EMPTY_4": "Aircraft 085",
      "__EMPTY_5": "1.2.1",
      "__EMPTY_6": "Lost at sea"
    },
    {
      "Data": 44510,
      "__EMPTY": "Payloads",
      "__EMPTY_1": "MWIR 3.6",
      "__EMPTY_2": "960202",
      "__EMPTY_3": "FMC",
      "__EMPTY_4": "Hangar",
      "__EMPTY_5": "1.3.7",
      "__EMPTY_6": ""
    },
    {
      "Data": 44510,
      "__EMPTY": "Payloads",
      "__EMPTY_1": "MWIR 3.6",
      "__EMPTY_2": "960198",
      "__EMPTY_3": "NMC",
      "__EMPTY_4": "Aircraft 080",
      "__EMPTY_5": "",
      "__EMPTY_6": ""
    }
  ],
  "USCG MIDGETT Deployed Gear": [
    {
      "Description": "DEPLOYED EQUIPMENT - Flight Deck",
      "QTY": 1,
      "Location": "Flight Deck"
    },
    {
      "Serial Number": "GCS XXX",
      "Description": "Deployed GCS ",
      "QTY": 1,
      "Location": "CONEX 2"
    },
    {
      "Description": "DEPLOYED BOX 2",
      "QTY": 1,
      "Location": "CONEX 2"
    },
    {
      "Description": "Additional Needed Items",
      "QTY": 1
    },
    {
      "Description": "AVWATCH",
      "QTY": 1,
      "Location": "CONEX 2"
    },
    {
      "__EMPTY_8": " "
    }
  ],
  "MIDGETT ANC Install": [
    {
      "Serial Number": 4009,
      "Description": "AVWATCH with Dome",
      "QTY": 1,
      "Location": "ANC / 0-4 Deck"
    },
    {
      "Serial Number": 4010,
      "Description": "AVWATCH with Dome",
      "QTY": 1,
      "Location": "ANC / 0-4 Deck"
    },
    {
      "Description": "Mast, Blu Force",
      "QTY": 2,
      "Location": "ANC / 0-4 Deck"
    },
    {
      "Part Number ": "N/A",
      "Serial Number": "N/A",
      "Description": "AVWATCH Power Supply",
      "QTY": 2,
      "Location": "ANC / 0-4 Deck"
    },
    {
      "Part Number ": "N/A",
      "Serial Number": "N/A",
      "Description": "CAT 6 and Conduit",
      "Location": "ANC / 0-4 Deck"
    },
    {
      "Part Number ": "N/A",
      "Serial Number": "N/A",
      "Description": "Extension Cord",
      "QTY": 2,
      "Location": "ANC / 0-4 Deck"
    },
    {
      "Part Number ": "N/A",
      "Serial Number": "N/A",
      "Description": "Cable Protector",
      "QTY": 3,
      "Location": "ANC / 0-4 Deck"
    },
    {
      "Part Number ": "NOTE - The USS Midgett is closed out minus the Antenna,Tri-Pods and CAT-6 cabling"
    }
  ]
}